MANIFEST.in
README.md
setup.py
torxlang/__init__.py
torxlang.egg-info/PKG-INFO
torxlang.egg-info/SOURCES.txt
torxlang.egg-info/dependency_links.txt
torxlang.egg-info/top_level.txt