Metadata-Version: 2.1
Name: torxlang
Version: 1.0.1
Summary: High API, Shortcut for most usefull functions, Special Features
Home-page: http://rx7.ir
Author: Ramin RX7
Author-email: rawmin.rx@gmail.com
License: MIT
Platform: UNKNOWN
Classifier: Programming Language :: Python :: 3
Requires-Python: >= 3.4
